py_to_mindustry/__init__.py
py_to_mindustry/basic.py
py_to_mindustry/ptm_types.py
py_to_mindustry/py_to_mindustry.py
py_to_mindustry-0.0.4.dist-info/LICENSE
py_to_mindustry-0.0.4.dist-info/METADATA
py_to_mindustry-0.0.4.dist-info/WHEEL
py_to_mindustry-0.0.4.dist-info/top_level.txt
py_to_mindustry-0.0.4.dist-info/RECORD
