Metadata-Version: 2.1
Name: py-to-mindustry
Version: 0.0.4
Summary: Translator from Python to Mindustry processor language
Home-page: https://github.com/vitmalok/py_to_mindustry
Author: Vitmalok
Author-email: vitmalok@gmail.com
License: UNKNOWN
Project-URL: Bug Tracker, https://github.com/vitmalok/py_to_mindustry/issues
Platform: UNKNOWN
Classifier: Programming Language :: Python :: 3.10
Classifier: License :: OSI Approved :: MIT License
Classifier: Operating System :: OS Independent
Requires-Python: >=3.10
License-File: LICENSE
